src/control_unit.vhd
library IEEE;
use IEEE.STD_LOGIC_1164.ALL;
use IEEE.NUMERIC_STD.ALL;

-- Main Control Unit - Decodes 6-bit MIPS opcode to generate control signals
entity Control_Unit is
    Port (
        opcode       : in  STD_LOGIC_VECTOR(5 downto 0);
        reset        : in  STD_LOGIC;        -- Reset signal
        
        reg_dst      : out STD_LOGIC_VECTOR(1 downto 0);  -- 00=rt, 01=rd, 10=$ra
        alu_src      : out STD_LOGIC;        -- ALU source select (0=reg, 1=immediate)
        mem_to_reg   : out STD_LOGIC_VECTOR(1 downto 0);  -- 00=ALU, 01=memory, 10=PC+4
        mem_write    : out STD_LOGIC;        -- Memory write enable
        mem_read     : out STD_LOGIC;        -- Memory read enable
        branch       : out STD_LOGIC;        -- Branch enable
        jump         : out STD_LOGIC;        -- Jump enable
        reg_write    : out STD_LOGIC;        -- Register write enable
        sign_or_zero : out STD_LOGIC;        -- Sign extend (1) or zero extend (0)
        alu_op       : out STD_LOGIC_VECTOR(1 downto 0)  -- ALU operation type
    );
end Control_Unit;

architecture Behavioral of Control_Unit is
begin

    process(opcode, reset)
    begin
        -- Default everything to a safe NOP-like state
        reg_dst <= "00";
        alu_src <= '0';
        mem_to_reg <= "00";
        mem_write <= '0';
        mem_read <= '0';
        branch <= '0';
        jump <= '0';
        reg_write <= '0';
        sign_or_zero <= '1';  -- Default: sign extend
        alu_op <= "00";
        
        if reset = '1' then
            -- Reset clears the control outputs
            reg_dst <= "00";
            alu_src <= '0';
            mem_to_reg <= "00";
            mem_write <= '0';
            mem_read <= '0';
            branch <= '0';
            jump <= '0';
            reg_write <= '0';
            sign_or_zero <= '1';
            alu_op <= "00";
        else
            -- Decode the 6-bit opcode into the control signals
            case opcode is
            
                -- R-type instructions
                when "000000" =>
                    -- Use rd and write the ALU result back to the register file
                    reg_dst <= "01";    -- rd is destination
                    alu_src <= '0';      -- Use register
                    mem_to_reg <= "00"; -- Use ALU result
                    mem_write <= '0';    -- No memory write
                    mem_read <= '0';     -- No memory read
                    branch <= '0';       -- No branch
                    jump <= '0';         -- No jump
                    reg_write <= '1';    -- Write to register
                    sign_or_zero <= '1'; -- Sign extend (not used for R-format)
                    alu_op <= "00";      -- Check function code
                
                -- Add immediate
                when "001000" =>
                    reg_dst <= "00";    -- rt is destination
                    alu_src <= '1';      -- Use immediate
                    mem_to_reg <= "00"; -- Use ALU result
                    mem_write <= '0';    -- No memory write
                    mem_read <= '0';     -- No memory read
                    branch <= '0';       -- No branch
                    jump <= '0';         -- No jump
                    reg_write <= '1';    -- Write to register
                    sign_or_zero <= '1'; -- Sign extend immediate
                    alu_op <= "11";      -- ADD operation
                
                -- Set less than immediate
                when "001010" =>
                    reg_dst <= "00";    -- rt is destination
                    alu_src <= '1';      -- Use immediate
                    mem_to_reg <= "00"; -- Use ALU result
                    mem_write <= '0';    -- No memory write
                    mem_read <= '0';     -- No memory read
                    branch <= '0';       -- No branch
                    jump <= '0';         -- No jump
                    reg_write <= '1';    -- Write to register
                    sign_or_zero <= '1'; -- Sign extend immediate
                    alu_op <= "10";      -- SLT operation
                
                -- Branch if equal
                when "000100" =>
                    reg_dst <= "00";    -- Don't care
                    alu_src <= '0';      -- Use register
                    mem_to_reg <= "00"; -- Don't care
                    mem_write <= '0';    -- No memory write
                    mem_read <= '0';     -- No memory read
                    branch <= '1';       -- Branch enabled
                    jump <= '0';         -- No jump
                    reg_write <= '0';    -- No register write
                    sign_or_zero <= '1'; -- Sign extend for branch offset
                    alu_op <= "01";      -- SUB (for comparison)
                
                -- Jump
                when "000010" =>
                    reg_dst <= "00";    -- Don't care
                    alu_src <= '0';      -- Don't care
                    mem_to_reg <= "00"; -- Don't care
                    mem_write <= '0';    -- No memory write
                    mem_read <= '0';     -- No memory read
                    branch <= '0';       -- No branch
                    jump <= '1';         -- Jump enabled
                    reg_write <= '0';    -- No register write
                    sign_or_zero <= '1'; -- Don't care
                    alu_op <= "00";      -- Don't care
                
                -- Jump and link
                when "000011" =>
                    reg_dst <= "10";    -- $ra is destination
                    alu_src <= '0';      -- Don't care
                    mem_to_reg <= "10"; -- Write PC + 4
                    mem_write <= '0';    -- No memory write
                    mem_read <= '0';     -- No memory read
                    branch <= '0';       -- No branch
                    jump <= '1';         -- Jump enabled
                    reg_write <= '1';    -- Write return address to $ra (reg 31)
                    sign_or_zero <= '1'; -- Don't care
                    alu_op <= "00";      -- Don't care
                
                -- Load word
                when "100011" =>
                    reg_dst <= "00";    -- rt is destination
                    alu_src <= '1';      -- Use immediate (for address offset)
                    mem_to_reg <= "01"; -- Use memory data
                    mem_write <= '0';    -- No memory write
                    mem_read <= '1';     -- Memory read enabled
                    branch <= '0';       -- No branch
                    jump <= '0';         -- No jump
                    reg_write <= '1';    -- Write to register
                    sign_or_zero <= '1'; -- Sign extend offset
                    alu_op <= "11";      -- ADD (for address calculation)
                
                -- Store word
                when "101011" =>
                    reg_dst <= "00";    -- Don't care
                    alu_src <= '1';      -- Use immediate (for address offset)
                    mem_to_reg <= "00"; -- Don't care
                    mem_write <= '1';    -- Memory write enabled
                    mem_read <= '0';     -- No memory read
                    branch <= '0';       -- No branch
                    jump <= '0';         -- No jump
                    reg_write <= '0';    -- No register write
                    sign_or_zero <= '1'; -- Sign extend offset
                    alu_op <= "11";      -- ADD (for address calculation)
                
                when others =>
                    -- Anything unsupported stays idle
                    reg_dst <= "00";
                    alu_src <= '0';
                    mem_to_reg <= "00";
                    mem_write <= '0';
                    mem_read <= '0';
                    branch <= '0';
                    jump <= '0';
                    reg_write <= '0';
                    sign_or_zero <= '1';
                    alu_op <= "00";
            
            end case;
        end if;
    end process;

end Behavioral;

testbench/control_unit_tb.vhd
library IEEE;
use IEEE.STD_LOGIC_1164.ALL;
use IEEE.NUMERIC_STD.ALL;

entity Control_Unit_tb is
end Control_Unit_tb;

architecture Behavioral of Control_Unit_tb is

        signal opcode    : STD_LOGIC_VECTOR(5 downto 0);
    signal reset     : STD_LOGIC := '0';
        signal reg_dst   : STD_LOGIC_VECTOR(1 downto 0);
    signal alu_src   : STD_LOGIC;
        signal mem_to_reg: STD_LOGIC_VECTOR(1 downto 0);
    signal mem_write : STD_LOGIC;
    signal mem_read  : STD_LOGIC;
    signal branch    : STD_LOGIC;
    signal jump      : STD_LOGIC;
    signal reg_write : STD_LOGIC;
    signal sign_or_zero : STD_LOGIC;
    signal alu_op    : STD_LOGIC_VECTOR(1 downto 0);

begin

    uut: entity work.Control_Unit
        port map (
            opcode => opcode,
            reset => reset,
            reg_dst => reg_dst,
            alu_src => alu_src,
            mem_to_reg => mem_to_reg,
            mem_write => mem_write,
            mem_read => mem_read,
            branch => branch,
            jump => jump,
            reg_write => reg_write,
            sign_or_zero => sign_or_zero,
            alu_op => alu_op
        );

    process
    begin
        -- Task 5: show the control signals for each opcode
        
        -- add
        opcode <= "000000";
        reset <= '0';
        wait for 10 ns;
        report "ADD: reg_dst="&std_logic'image(reg_dst(1))&std_logic'image(reg_dst(0))&" alu_src="&std_logic'image(alu_src)&
                " mem_to_reg="&std_logic'image(mem_to_reg(1))&std_logic'image(mem_to_reg(0))&" mem_write="&std_logic'image(mem_write)&
                " mem_read="&std_logic'image(mem_read)&" branch="&std_logic'image(branch)&
                " jump="&std_logic'image(jump)&" reg_write="&std_logic'image(reg_write)&
                " sign_or_zero="&std_logic'image(sign_or_zero) severity note;

        -- addi
        opcode <= "001000";
        wait for 10 ns;
        report "ADDI: reg_dst="&std_logic'image(reg_dst(1))&std_logic'image(reg_dst(0))&" alu_src="&std_logic'image(alu_src)&
                " mem_to_reg="&std_logic'image(mem_to_reg(1))&std_logic'image(mem_to_reg(0))&" mem_write="&std_logic'image(mem_write)&
                " mem_read="&std_logic'image(mem_read)&" branch="&std_logic'image(branch)&
                " jump="&std_logic'image(jump)&" reg_write="&std_logic'image(reg_write)&
                " sign_or_zero="&std_logic'image(sign_or_zero) severity note;

        -- slti
        opcode <= "001010";
        wait for 10 ns;
        report "SLTI: reg_dst="&std_logic'image(reg_dst(1))&std_logic'image(reg_dst(0))&" alu_src="&std_logic'image(alu_src)&
                " mem_to_reg="&std_logic'image(mem_to_reg(1))&std_logic'image(mem_to_reg(0))&" mem_write="&std_logic'image(mem_write)&
                " mem_read="&std_logic'image(mem_read)&" branch="&std_logic'image(branch)&
                " jump="&std_logic'image(jump)&" reg_write="&std_logic'image(reg_write)&
                " sign_or_zero="&std_logic'image(sign_or_zero) severity note;

        -- beq
        opcode <= "000100";
        wait for 10 ns;
        report "BEQ: reg_dst="&std_logic'image(reg_dst(1))&std_logic'image(reg_dst(0))&" alu_src="&std_logic'image(alu_src)&
                " mem_to_reg="&std_logic'image(mem_to_reg(1))&std_logic'image(mem_to_reg(0))&" mem_write="&std_logic'image(mem_write)&
                " mem_read="&std_logic'image(mem_read)&" branch="&std_logic'image(branch)&
                " jump="&std_logic'image(jump)&" reg_write="&std_logic'image(reg_write)&
                " sign_or_zero="&std_logic'image(sign_or_zero) severity note;

        -- j
        opcode <= "000010";
        wait for 10 ns;
        report "J: reg_dst="&std_logic'image(reg_dst(1))&std_logic'image(reg_dst(0))&" alu_src="&std_logic'image(alu_src)&
                " mem_to_reg="&std_logic'image(mem_to_reg(1))&std_logic'image(mem_to_reg(0))&" mem_write="&std_logic'image(mem_write)&
                " mem_read="&std_logic'image(mem_read)&" branch="&std_logic'image(branch)&
                " jump="&std_logic'image(jump)&" reg_write="&std_logic'image(reg_write)&
                " sign_or_zero="&std_logic'image(sign_or_zero) severity note;

        -- jal
        opcode <= "000011";
        wait for 10 ns;
        report "JAL: reg_dst="&std_logic'image(reg_dst(1))&std_logic'image(reg_dst(0))&" alu_src="&std_logic'image(alu_src)&
                " mem_to_reg="&std_logic'image(mem_to_reg(1))&std_logic'image(mem_to_reg(0))&" mem_write="&std_logic'image(mem_write)&
                " mem_read="&std_logic'image(mem_read)&" branch="&std_logic'image(branch)&
                " jump="&std_logic'image(jump)&" reg_write="&std_logic'image(reg_write)&
                " sign_or_zero="&std_logic'image(sign_or_zero) severity note;

        -- lw
        opcode <= "100011";
        wait for 10 ns;
        report "LW: reg_dst="&std_logic'image(reg_dst(1))&std_logic'image(reg_dst(0))&" alu_src="&std_logic'image(alu_src)&
                " mem_to_reg="&std_logic'image(mem_to_reg(1))&std_logic'image(mem_to_reg(0))&" mem_write="&std_logic'image(mem_write)&
                " mem_read="&std_logic'image(mem_read)&" branch="&std_logic'image(branch)&
                " jump="&std_logic'image(jump)&" reg_write="&std_logic'image(reg_write)&
                " sign_or_zero="&std_logic'image(sign_or_zero) severity note;

        -- sw
        opcode <= "101011";
        wait for 10 ns;
        report "SW: reg_dst="&std_logic'image(reg_dst(1))&std_logic'image(reg_dst(0))&" alu_src="&std_logic'image(alu_src)&
                " mem_to_reg="&std_logic'image(mem_to_reg(1))&std_logic'image(mem_to_reg(0))&" mem_write="&std_logic'image(mem_write)&
                " mem_read="&std_logic'image(mem_read)&" branch="&std_logic'image(branch)&
                " jump="&std_logic'image(jump)&" reg_write="&std_logic'image(reg_write)&
                " sign_or_zero="&std_logic'image(sign_or_zero) severity note;

        report "Control unit test completed!" severity note;
        wait;

    end process;

end Behavioral;

waveforms/control_unit.vcd
$date
  Fri Apr 03 10:39:55 2026
$end
$version
  GHDL v0
$end
$timescale
  1 fs
$end
$scope module standard $end
$upscope $end
$scope module textio $end
$upscope $end
$scope module std_logic_1164 $end
$upscope $end
$scope module numeric_std $end
$upscope $end
$scope module control_unit_tb $end
$var reg 6 ! opcode[5:0] $end
$var reg 1 " reset $end
$var reg 2 # reg_dst[1:0] $end
$var reg 1 $ alu_src $end
$var reg 2 % mem_to_reg[1:0] $end
$var reg 1 & mem_write $end
$var reg 1 ' mem_read $end
$var reg 1 ( branch $end
$var reg 1 ) jump $end
$var reg 1 * reg_write $end
$var reg 1 + sign_or_zero $end
$var reg 2 , alu_op[1:0] $end
$scope module uut $end
$var reg 6 - opcode[5:0] $end
$var reg 1 . reset $end
$var reg 2 / reg_dst[1:0] $end
$var reg 1 0 alu_src $end
$var reg 2 1 mem_to_reg[1:0] $end
$var reg 1 2 mem_write $end
$var reg 1 3 mem_read $end
$var reg 1 4 branch $end
$var reg 1 5 jump $end
$var reg 1 6 reg_write $end
$var reg 1 7 sign_or_zero $end
$var reg 2 8 alu_op[1:0] $end
$upscope $end
$upscope $end
$enddefinitions $end
#0
b000000 !
0"
b01 #
0$
b00 %
0&
0'
0(
0)
1*
1+
b00 ,
b000000 -
0.
b01 /
00
b00 1
02
03
04
05
16
17
b00 8
#10000000
b001000 !
b00 #
1$
b11 ,
b001000 -
b00 /
10
16
b11 8
#20000000
b001010 !
b10 ,
b001010 -
10
16
b10 8
#30000000
b000100 !
0$
1(
0*
b01 ,
b000100 -
00
14
06
b01 8
#40000000
b000010 !
0(
1)
b00 ,
b000010 -
04
15
b00 8
#50000000
b000011 !
b10 #
b10 %
1*
b000011 -
b10 /
b10 1
15
16
#60000000
b100011 !
b00 #
1$
b01 %
1'
0)
b11 ,
b100011 -
b00 /
10
b01 1
13
05
16
b11 8
#70000000
b101011 !
b00 %
1&
0'
0*
b101011 -
10
b00 1
12
03
06
b11 8
