src/data_memory.vhd
library IEEE;
use IEEE.STD_LOGIC_1164.ALL;
use IEEE.NUMERIC_STD.ALL;

entity Data_Memory is
    Port (
        clk              : in  STD_LOGIC;
        mem_access_addr  : in  STD_LOGIC_VECTOR(31 downto 0);
        mem_write_data   : in  STD_LOGIC_VECTOR(31 downto 0);
        mem_write_en     : in  STD_LOGIC;
        mem_read         : in  STD_LOGIC;
        mem_read_data    : out STD_LOGIC_VECTOR(31 downto 0)
    );
end Data_Memory;

architecture Behavioral of Data_Memory is

    type memory_array is array (0 to 255) of STD_LOGIC_VECTOR(31 downto 0);
    signal RAM : memory_array := (others => (others => '0'));

    signal addr_index : integer range 0 to 255;

begin

    -- Use the lower address bits to pick the memory location
    addr_index <= to_integer(unsigned(mem_access_addr(7 downto 0)));

    process(clk)
    begin
        if rising_edge(clk) then

            -- Store data when write enable is active
            if mem_write_en = '1' then
                RAM(addr_index) <= mem_write_data;
            end if;

            -- Output the selected word when read is active
            if mem_read = '1' then
                mem_read_data <= RAM(addr_index);
            else
                mem_read_data <= (others => '0');
            end if;

        end if;
    end process;

end Behavioral;

testbench/data_memory_tb.vhd
library IEEE;
use IEEE.STD_LOGIC_1164.ALL;
use IEEE.NUMERIC_STD.ALL;

entity Data_Memory_tb is
end Data_Memory_tb;

architecture Behavioral of Data_Memory_tb is

    signal clk              : STD_LOGIC := '0';
    signal mem_access_addr  : STD_LOGIC_VECTOR(31 downto 0) := (others => '0');
    signal mem_write_data   : STD_LOGIC_VECTOR(31 downto 0) := (others => '0');
    signal mem_write_en     : STD_LOGIC := '0';
    signal mem_read         : STD_LOGIC := '0';
    signal mem_read_data    : STD_LOGIC_VECTOR(31 downto 0);

begin

    uut: entity work.Data_Memory
        port map (
            clk => clk,
            mem_access_addr => mem_access_addr,
            mem_write_data => mem_write_data,
            mem_write_en => mem_write_en,
            mem_read => mem_read,
            mem_read_data => mem_read_data
        );

    -- Clock generator
    process
    begin
        while true loop
            clk <= '0';
            wait for 5 ns;
            clk <= '1';
            wait for 5 ns;
        end loop;
    end process;

    -- Test cases from the assignment
    process
    begin

        -- Test 1: write 1024 to address 2 and read it back
        mem_access_addr <= std_logic_vector(to_unsigned(2, 32));
        mem_write_data  <= std_logic_vector(to_unsigned(1024, 32));
        mem_write_en    <= '1';
        wait for 10 ns;

        mem_write_en <= '0';

        -- Read the value back
        mem_read <= '1';
        wait for 10 ns;

        mem_read <= '0';


        -- Test 2: write 429496 to address 4 and read it back
        mem_access_addr <= std_logic_vector(to_unsigned(4, 32));
        mem_write_data  <= std_logic_vector(to_unsigned(429496, 32));
        mem_write_en    <= '1';
        wait for 10 ns;

        mem_write_en <= '0';

        -- Read the value back
        mem_read <= '1';
        wait for 10 ns;

        mem_read <= '0';

        wait;

    end process;

end Behavioral;

waveforms/memory.vcd
$date
  Thu Apr 02 18:47:19 2026
$end
$version
  GHDL v0
$end
$timescale
  1 fs
$end
$scope module standard $end
$upscope $end
$scope module std_logic_1164 $end
$upscope $end
$scope module numeric_std $end
$upscope $end
$scope module data_memory_tb $end
$var reg 1 ! clk $end
$var reg 32 " mem_access_addr[31:0] $end
$var reg 32 # mem_write_data[31:0] $end
$var reg 1 $ mem_write_en $end
$var reg 1 % mem_read $end
$var reg 32 & mem_read_data[31:0] $end
$scope module uut $end
$var reg 1 ' clk $end
$var reg 32 ( mem_access_addr[31:0] $end
$var reg 32 ) mem_write_data[31:0] $end
$var reg 1 * mem_write_en $end
$var reg 1 + mem_read $end
$var reg 32 , mem_read_data[31:0] $end
$comment ram is not handled $end
$var integer 32 - addr_index $end
$upscope $end
$upscope $end
$enddefinitions $end
#0
0!
b00000000000000000000000000000010 "
b00000000000000000000010000000000 #
1$
0%
bUUUUUUUUUUUUUUUUUUUUUUUUUUUUUUUU &
0'
b00000000000000000000000000000010 (
b00000000000000000000010000000000 )
1*
0+
bUUUUUUUUUUUUUUUUUUUUUUUUUUUUUUUU ,
b10 -
#5000000
1!
b00000000000000000000000000000000 &
1'
b00000000000000000000000000000000 ,
#10000000
0!
0$
1%
0'
0*
1+
#15000000
1!
b00000000000000000000010000000000 &
1'
b00000000000000000000010000000000 ,
#20000000
0!
b00000000000000000000000000000100 "
b00000000000001101000110110111000 #
1$
0%
0'
b00000000000000000000000000000100 (
b00000000000001101000110110111000 )
1*
0+
b100 -
#25000000
1!
b00000000000000000000000000000000 &
1'
b00000000000000000000000000000000 ,
#30000000
0!
0$
1%
0'
0*
1+
#35000000
1!
b00000000000001101000110110111000 &
1'
b00000000000001101000110110111000 ,
#40000000
0!
0%
0'
0+
#45000000
1!
b00000000000000000000000000000000 &
1'
b00000000000000000000000000000000 ,
